tp_folder_dl/__about__.py
tp_folder_dl/__init__.py
tp_folder_dl/__main__.py
tp_folder_dl/tp_folder_dl.py
tp_folder_dl-0.1.1.dist-info/METADATA
tp_folder_dl-0.1.1.dist-info/WHEEL
tp_folder_dl-0.1.1.dist-info/entry_points.txt
tp_folder_dl-0.1.1.dist-info/licenses/LICENSE.txt
tp_folder_dl-0.1.1.dist-info/RECORD
