Metadata-Version: 2.4
Name: tp-folder-dl
Version: 0.1.1
Summary: Automatic download of PO files from the TranslationProject
Project-URL: Documentation, https://github.com/s-ball/tp-folder-dl#readme
Project-URL: Issues, https://github.com/s-ball/tp-folder-dl/issues
Project-URL: Source, https://github.com/s-ball/tp-folder-dl
Author-email: s-ball <s-ball@laposte.net>
License-Expression: MIT
License-File: LICENSE.txt
Classifier: Development Status :: 4 - Beta
Classifier: Programming Language :: Python
Classifier: Programming Language :: Python :: 3.9
Classifier: Programming Language :: Python :: 3.10
Classifier: Programming Language :: Python :: 3.11
Classifier: Programming Language :: Python :: 3.12
Classifier: Programming Language :: Python :: 3.13
Classifier: Programming Language :: Python :: Implementation :: CPython
Requires-Python: >=3.9
Requires-Dist: bs4
